TechnicalNotesOnUsingDataScienceArtificialIntelligence/README.md
TechnicalNotesOnUsingDataScienceArtificialIntelligence/__init__.py
TechnicalNotesOnUsingDataScienceArtificialIntelligence/__main__.py
TechnicalNotesOnUsingDataScienceArtificialIntelligence/file.epub
TechnicalNotesOnUsingDataScienceArtificialIntelligence/index.html
TechnicalNotesOnUsingDataScienceArtificialIntelligence/css/__init__.py
TechnicalNotesOnUsingDataScienceArtificialIntelligence/css/annotations.css
TechnicalNotesOnUsingDataScienceArtificialIntelligence/css/main.css
TechnicalNotesOnUsingDataScienceArtificialIntelligence/css/normalize.css
TechnicalNotesOnUsingDataScienceArtificialIntelligence/css/popup.css
TechnicalNotesOnUsingDataScienceArtificialIntelligence/font/__init__.py
TechnicalNotesOnUsingDataScienceArtificialIntelligence/font/fontello.eot
TechnicalNotesOnUsingDataScienceArtificialIntelligence/font/fontello.svg
TechnicalNotesOnUsingDataScienceArtificialIntelligence/font/fontello.ttf
TechnicalNotesOnUsingDataScienceArtificialIntelligence/font/fontello.woff
TechnicalNotesOnUsingDataScienceArtificialIntelligence/img/__init__.py
TechnicalNotesOnUsingDataScienceArtificialIntelligence/img/annotator-glyph-sprite.png
TechnicalNotesOnUsingDataScienceArtificialIntelligence/img/annotator-icon-sprite.png
TechnicalNotesOnUsingDataScienceArtificialIntelligence/img/apple-touch-icon.png
TechnicalNotesOnUsingDataScienceArtificialIntelligence/img/cancelfullscreen.png
TechnicalNotesOnUsingDataScienceArtificialIntelligence/img/close.png
TechnicalNotesOnUsingDataScienceArtificialIntelligence/img/fullscreen.png
TechnicalNotesOnUsingDataScienceArtificialIntelligence/img/loader.gif
TechnicalNotesOnUsingDataScienceArtificialIntelligence/img/menu-icon.png
TechnicalNotesOnUsingDataScienceArtificialIntelligence/img/save.png
TechnicalNotesOnUsingDataScienceArtificialIntelligence/img/saved.png
TechnicalNotesOnUsingDataScienceArtificialIntelligence/img/settings-s.png
technical_notes_on_using_data_science_artificial_intelligence-2024.3.4.0.dist-info/METADATA
technical_notes_on_using_data_science_artificial_intelligence-2024.3.4.0.dist-info/WHEEL
technical_notes_on_using_data_science_artificial_intelligence-2024.3.4.0.dist-info/entry_points.txt
technical_notes_on_using_data_science_artificial_intelligence-2024.3.4.0.dist-info/top_level.txt
technical_notes_on_using_data_science_artificial_intelligence-2024.3.4.0.dist-info/RECORD
